pibake/__init__.py
pibake/cli.py
pibake/disks.py
pibake/settings.py
pibake/utils.py
pibake-0.2.7.dist-info/DESCRIPTION.rst
pibake-0.2.7.dist-info/METADATA
pibake-0.2.7.dist-info/RECORD
pibake-0.2.7.dist-info/WHEEL
pibake-0.2.7.dist-info/entry_points.txt
pibake-0.2.7.dist-info/metadata.json
pibake-0.2.7.dist-info/top_level.txt
