Metadata-Version: 2.0
Name: pibake
Version: 0.2.7
Summary: Fetches and Manages Raspberry PI Images
Home-page: https://github.com/sthysel/pibake
Author: Thys Meintjes
Author-email: sthysel@gmail.com
License: GPLv2
Download-URL: https://github.com/sthysel/pibake/archive/v0.2.7.tar.gz
Keywords: Raspberry PI Downloader
Platform: UNKNOWN
Classifier: Development Status :: 5 - Production/Stable
Classifier: Programming Language :: Python :: 3
Classifier: Intended Audience :: Education
Classifier: Intended Audience :: End Users/Desktop
Classifier: Intended Audience :: Science/Research
Classifier: Operating System :: Unix
Classifier: Topic :: Education
Classifier: Topic :: Utilities
Requires-Dist: click
Requires-Dist: psutil
Requires-Dist: pyxdg
Requires-Dist: requests
Requires-Dist: xdg
